optibess_algorithm/__init__.py
optibess_algorithm/constants.py
optibess_algorithm/financial_calculator.py
optibess_algorithm/output_calculator.py
optibess_algorithm/power_storage.py
optibess_algorithm/power_system_optimizer.py
optibess_algorithm/producers.py
optibess_algorithm/pv_output_calculator.py
optibess_algorithm/sam-library-cec-inverters-2019-03-05.csv
optibess_algorithm/sam-library-cec-modules-2019-03-05.csv
optibess_algorithm/sam-library-sandia-modules-2015-6-30.csv
optibess_algorithm/test.csv
optibess_algorithm/utils.py
optibess_algorithm-0.1.1.dist-info/LICENSE
optibess_algorithm-0.1.1.dist-info/METADATA
optibess_algorithm-0.1.1.dist-info/WHEEL
optibess_algorithm-0.1.1.dist-info/top_level.txt
optibess_algorithm-0.1.1.dist-info/RECORD
