Metadata-Version: 2.1
Name: optibess_algorithm
Version: 0.1.1
Summary: Optibess Algorithm is a python 3.10+ library for simulating and optimizing a photovoltaic system with power storage.
Author: El-mor Renewable Energies Dev Team
License: MIT License
Project-URL: homepage, https://github.com/pvstorageoptimization/Optibess_algorithm
Project-URL: docs, https://optibess-algorithm.readthedocs.io
Keywords: solar,PV,optimization,power storage,BESS
Classifier: Programming Language :: Python :: 3
Classifier: Programming Language :: Python :: 3 :: Only
Classifier: Programming Language :: Python :: 3.10
Classifier: Intended Audience :: Science/Research
Classifier: Operating System :: OS Independent
Classifier: Topic :: Scientific/Engineering
Requires-Python: >=3.10
License-File: LICENSE
Requires-Dist: numpy >=1.24.2
Requires-Dist: numpy-financial ==1.0.0
Requires-Dist: pandas >=2.1.3
Requires-Dist: matplotlib >=3.7.1
Requires-Dist: nevergrad ==0.6.0
Requires-Dist: timezonefinder ==6.1.9
Requires-Dist: pvlib ==0.10.2
Requires-Dist: solarfactors >=1.5.3
Provides-Extra: testing
Requires-Dist: flake8 >=6.1.0 ; extra == 'testing'
Requires-Dist: mypy >=1.7.0 ; extra == 'testing'
Requires-Dist: tox >=4.11.3 ; extra == 'testing'
